dart_cli/__init__.py
dart_cli/auth/__init__.py
dart_cli/auth/retrieve_token.py
dart_cli/cli/__init__.py
dart_cli/cli/dart.py
dart_cli/cli/global_options.py
dart_cli/corpex/__init__.py
dart_cli/corpex/aggregate.py
dart_cli/corpex/corpex_utilties.py
dart_cli/corpex/search.py
dart_cli/corpex/shave.py
dart_cli/dart_context/__init__.py
dart_cli/dart_context/auth_config.py
dart_cli/dart_context/dart_config.py
dart_cli/dart_context/dart_context.py
dart_cli/dart_context/docker_config.py
dart_cli/dart_context/kafka_config.py
dart_cli/dart_context/test_dart_context.py
dart_cli/dart_context/dart_environment/__init__.py
dart_cli/dart_context/dart_environment/dart_environment.py
dart_cli/dart_context/dart_environment/dart_environment_type.py
dart_cli/dart_context/dart_environment/env_type_custom.py
dart_cli/dart_context/dart_environment/env_type_default.py
dart_cli/dart_context/dart_environment/env_type_tst.py
dart_cli/dart_kafka/__init__.py
dart_cli/dart_kafka/kafka_integration.py
dart_cli/dart_kafka/message_printer.py
dart_cli/docker_commands/__init__.py
dart_cli/docker_commands/docker_execs.py
dart_cli/forklift/__init__.py
dart_cli/forklift/submit.py
dart_cli/health/__init__.py
dart_cli/health/dart_healthcheck.py
dart_cli/local/__init__.py
dart_cli/local/filter.py
dart_cli/local/hash.py
dart_cli/local/list.py
dart_cli/local/post.py
dart_cli/local/update.py
dart_cli/messages/__init__.py
dart_cli/messages/read.py
dart_cli/pipeline/__init__.py
dart_cli/pipeline/clean.py
dart_cli/pipeline/commands.py
dart_cli/pipeline/deploy.py
dart_cli/pipeline/diab.py
dart_cli/pipeline/provision.py
dart_cli/profiles/__init__.py
dart_cli/profiles/manage_profiles.py
dart_cli/readers/__init__.py
dart_cli/reprocess/__init__.py
dart_cli/reprocess/reprocess.py
dart_cli/retrieve/__init__.py
dart_cli/retrieve/cdr_archive.py
dart_cli/retrieve/cdr_retrieval.py
dart_cli/ssh/__init__.py
dart_cli/ssh/ssh.py
dart_cli/tenants/__init__.py
dart_cli/tenants/add_tenants.py
dart_cli/tenants/ls_tenants.py
dart_cli-3.1.49.dist-info/LICENSE
dart_cli-3.1.49.dist-info/METADATA
dart_cli-3.1.49.dist-info/WHEEL
dart_cli-3.1.49.dist-info/entry_points.txt
dart_cli-3.1.49.dist-info/top_level.txt
dart_cli-3.1.49.dist-info/RECORD
