Metadata-Version: 2.1
Name: dart-cli
Version: 3.1.49
Summary: Data Acquisition and Reason Toolkit (DART) command-line interface
Home-page: https://github.com/twosixlabs-dart/dart-cli
Author: John Hungerford
Author-email: john.hungerford@twosixtech.com
License: UNKNOWN
Platform: UNKNOWN
Classifier: Programming Language :: Python :: 3
Classifier: License :: OSI Approved :: GNU Affero General Public License v3
Classifier: Programming Language :: Python :: 3.9
License-File: LICENSE
Requires-Dist: click
Requires-Dist: pytest
Requires-Dist: boto3
Requires-Dist: botocore
Requires-Dist: requests
Requires-Dist: docker
Requires-Dist: dockerpty
Requires-Dist: pyjwt
Requires-Dist: kafka-python
